nia_ai_api_client/__init__.py
nia_ai_api_client/api/__init__.py
nia_ai_api_client/api/analytics/__init__.py
nia_ai_api_client/api/analytics/get_activity_summary_api_analytics_activity_summary_get.py
nia_ai_api_client/api/analytics/get_api_activities_api_analytics_api_activities_get.py
nia_ai_api_client/api/analytics/get_usage_timeseries_api_analytics_usage_timeseries_get.py
nia_ai_api_client/api/api_keys/__init__.py
nia_ai_api_client/api/api_keys/create_new_api_key_api_keys_post.py
nia_ai_api_client/api/api_keys/list_api_keys_api_keys_get.py
nia_ai_api_client/api/api_keys/list_projects_endpoint_api_keys_projects_get.py
nia_ai_api_client/api/api_keys/remove_api_key_api_keys_key_id_delete.py
nia_ai_api_client/api/api_keys/validate_api_key_api_keys_validate_key_get.py
nia_ai_api_client/api/api_projects/__init__.py
nia_ai_api_client/api/api_projects/update_project_model_api_projects_project_id_model_patch.py
nia_ai_api_client/api/billing/__init__.py
nia_ai_api_client/api/billing/add_payment_method_api_billing_add_payment_method_post.py
nia_ai_api_client/api/billing/cancel_organization_subscription_api_billing_organization_org_id_cancel_post.py
nia_ai_api_client/api/billing/cancel_subscription_api_billing_cancel_post.py
nia_ai_api_client/api/billing/create_checkout_session_api_billing_create_checkout_session_post.py
nia_ai_api_client/api/billing/create_organization_portal_session_api_billing_organization_org_id_portal_session_post.py
nia_ai_api_client/api/billing/create_organization_subscription_api_billing_organization_create_subscription_post.py
nia_ai_api_client/api/billing/create_portal_session_api_billing_create_portal_session_post.py
nia_ai_api_client/api/billing/get_api_usage_api_billing_api_usage_get.py
nia_ai_api_client/api/billing/get_api_usage_details_api_billing_api_usage_details_get.py
nia_ai_api_client/api/billing/get_organization_subscription_api_billing_organization_org_id_subscription_get.py
nia_ai_sdk-1.0.0.dist-info/METADATA
nia_ai_sdk-1.0.0.dist-info/WHEEL
nia_ai_sdk-1.0.0.dist-info/RECORD
